epsf/__init__.py
epsf/_version.py
epsf/bayes.py
epsf/epsf.py
epsf/grid.py
epsf/plot.py
epsf/utils.py
epsf-0.1.0.dist-info/METADATA
epsf-0.1.0.dist-info/WHEEL
epsf-0.1.0.dist-info/licenses/LICENSE
epsf-0.1.0.dist-info/RECORD
